.gitignore
LICENSE
LICENSE.txt
MANIFEST.in
README.md
requirements.txt
setup.cfg
setup.py
docs/Makefile
docs/make.bat
docs/source/buildNetworks.rst
docs/source/conf.py
docs/source/fileUtils.rst
docs/source/index.rst
docs/source/odePrint.rst
docs/source/parameterScanning.rst
docs/source/plotting.rst
docs/source/prettyTabular.rst
teUtils/__init__.py
teUtils/_version.py
teUtils/buildNetworks.py
teUtils/fileUtils.py
teUtils/odePrint.py
teUtils/parameterScanning.py
teUtils/plotting.py
teUtils/prettyTabular.py
teUtils/testParameterScanning.py
teUtils.egg-info/PKG-INFO
teUtils.egg-info/SOURCES.txt
teUtils.egg-info/dependency_links.txt
teUtils.egg-info/requires.txt
teUtils.egg-info/top_level.txt