Metadata-Version: 2.1
Name: teUtils
Version: 2.5
Summary: Utilities for Tellurium
Home-page: http://tellurium.analogmachine.org
Author-email: hsauro@uw.edu
License: MIT
Platform: UNKNOWN
Classifier: License :: OSI Approved :: MIT License
Classifier: Programming Language :: Python :: 3.6
Classifier: Programming Language :: Python :: 3.7
Classifier: Programming Language :: Python :: 3.8
Classifier: Operating System :: OS Independent
Requires-Python: >=3.6
